mynameisvarun/__init__.py
mynameisvarun/christmas.py
mynameisvarun/conversation.py
mynameisvarun/xmas.py
mynameisvarun/xmas_turtle.py
mynameisvarun-1.4.1.dist-info/LICENCE.txt
mynameisvarun-1.4.1.dist-info/METADATA
mynameisvarun-1.4.1.dist-info/WHEEL
mynameisvarun-1.4.1.dist-info/top_level.txt
mynameisvarun-1.4.1.dist-info/RECORD
